{
  "company": "제이엔케이글로벌",
  "hint": "코스닥 상장사. 업종: 일반 목적용 기계 제조업. 주요제품: 산업용가열로, 수소충전소",
  "sector": "일반 목적용 기계 제조업",
  "product": "산업용가열로, 수소충전소",
  "public_profile": "제이엔케이글로벌은 정유 및 석유화학 플랜트의 핵심 설비인 산업용 가열로(Fired Heater)를 설계·제작·시공하는 코스닥 상장 기업입니다. 주력 제품인 산업용 가열로 외에도 자체 기술로 개발한 수소추출기 및 수소충전소 구축 등 수소 에너지 사업을 신성장 동력으로 육성하고 있습니다. 주요 고객사는 국내외 대형 정유·석유화학 기업 및 EPC 업체이며, 최근 인도 국영 정유사(BPCL)로부터 창사 이래 최대 규모인 4,100억 원대 프로젝트를 수주하는 등 글로벌 시장에서 기술력을 인정받고 있습니다. 또한, 수소전문기업 선정 및 세계일류상품 선정 등 다수의 정부 인증과 수상 실적을 보유하고 있습니다. 협업 관점에서는 30년 이상의 엔지니어링 노하우와 글로벌 메이저 기업 대상의 프로젝트 수행 경험을 바탕으로, 고난도 설계 및 턴키(Turn-key) 방식의 엔지니어링 솔루션을 제공할 수 있는 역량을 갖춘 파트너로 평가됩니다.",
  "provenance": "grounded",
  "source": "kosdaq_krx",
  "researched_at": "2026-07-23T19:18:41"
}