{
  "company": "큐라티스",
  "hint": "코스닥 상장사. 업종: 자연과학 및 공학 연구개발업. 주요제품: 백신 및 면역증강제 개발제조업, CMO/CDMO",
  "sector": "자연과학 및 공학 연구개발업",
  "product": "백신 및 면역증강제 개발제조업, CMO/CDMO",
  "public_profile": "큐라티스는 백신 후보물질의 연구개발부터 임상, 상업화 생산까지 전 과정을 수행하는 바이오 의약품 연구개발 및 제조 기업입니다. 주요 파이프라인으로 성인 및 청소년용 결핵 백신(QTP101)과 mRNA 기반 코로나19 백신(QTP104)을 보유하고 있으며, 면역증강제 및 세포치료제 플랫폼 기술을 핵심 역량으로 합니다. 주요 시장은 글로벌 백신 및 바이오 의약품 위탁개발생산(CDMO) 분야이며, 국내외 제약·바이오 기업을 주요 고객으로 확보하고 있습니다. 최근에는 인벤티지랩과 장기지속형 주사제 전용 CDMO 생산라인 구축 계약을 체결하는 등 사업 다각화와 생산 효율화에 집중하고 있습니다. 충북 오송에 cGMP, EU-GMP, KGMP 인증을 획득한 대규모 바이오 플랜트를 운영하며 임상 시료부터 상업용 대량 생산까지 가능한 전주기 역량을 검증받았습니다. 과거 중소벤처기업부 장관 표창 등 다수의 정부 포상을 통해 기술력과 산업 기여도를 인정받은 바 있으나, 최근 재무구조 개선을 위한 무상감자를 결정하는 등 경영 효율화와 상장 유지에 주력하고 있습니다. B2B 협상 관점에서는 자체 생산 인프라를 활용한 맞춤형 CDMO 서비스 제공이 강점이나, 재무적 안정성 및 파이프라인의 상업화 성과를 면밀히 검토할 필요가 있습니다.",
  "provenance": "grounded",
  "source": "kosdaq_krx",
  "researched_at": "2026-07-23T19:18:20"
}